{
  "_comment": "V3 L3에 해당 활동이 없는 IT·의료·업무 영역의 한국어 표현을 가장 가까운 L2로 연결하는 브리지. confidence_floor는 최소 보장값입니다 (시니어 3 수정안 5). target_l2가 null이면 V3 갭이 심각하여 NEEDS_CONTEXT로 폴백됩니다. 모든 target_l2는 V3 L2_META에서 검증되었습니다.",
  "version": "1.0.0",
  "entries": [
    {"keyword": "정산",               "target_l2": "banking_routine",    "confidence_floor": 0.55, "note": "정산·결산을 은행 업무로 매핑"},
    {"keyword": "스프린트 플래닝",      "target_l2": "work_meetings",      "confidence_floor": 0.55},
    {"keyword": "스프린트플래닝",       "target_l2": "work_meetings",      "confidence_floor": 0.55},
    {"keyword": "스탠드업 미팅",        "target_l2": "work_meetings",      "confidence_floor": 0.55},
    {"keyword": "스탠드업",            "target_l2": "work_meetings",      "confidence_floor": 0.5},
    {"keyword": "칸반 보드",           "target_l2": "work_planning",      "confidence_floor": 0.5},
    {"keyword": "피드백 수집",         "target_l2": "work_planning",      "confidence_floor": 0.45},
    {"keyword": "피드백 정리",         "target_l2": "work_planning",      "confidence_floor": 0.45},
    {"keyword": "리뷰 미팅",           "target_l2": "work_meetings",      "confidence_floor": 0.5},
    {"keyword": "킥오프",              "target_l2": "work_meetings",      "confidence_floor": 0.55},
    {"keyword": "킥오프 미팅",         "target_l2": "work_meetings",      "confidence_floor": 0.55},
    {"keyword": "1on1",               "target_l2": "work_meetings",      "confidence_floor": 0.6},
    {"keyword": "원온원",              "target_l2": "work_meetings",      "confidence_floor": 0.55},
    {"keyword": "브레인스토밍",        "target_l2": "work_core",          "confidence_floor": 0.5},

    {"keyword": "API 설계",            "target_l2": "work_core",          "confidence_floor": 0.55, "note": "V3에 coding_dev L2가 없어 work_core로 매핑"},
    {"keyword": "API",                "target_l2": "work_core",          "confidence_floor": 0.45},
    {"keyword": "DB 쿼리",             "target_l2": "work_core",          "confidence_floor": 0.55},
    {"keyword": "DB 설계",             "target_l2": "work_core",          "confidence_floor": 0.55},
    {"keyword": "쿼리 최적화",         "target_l2": "work_core",          "confidence_floor": 0.5},
    {"keyword": "스키마 설계",         "target_l2": "work_core",          "confidence_floor": 0.55},
    {"keyword": "git 커밋",            "target_l2": "work_core",          "confidence_floor": 0.55},
    {"keyword": "PR 리뷰",             "target_l2": "work_core",          "confidence_floor": 0.55},
    {"keyword": "MR 리뷰",             "target_l2": "work_core",          "confidence_floor": 0.55},
    {"keyword": "코드 리뷰",           "target_l2": "work_core",          "confidence_floor": 0.55},
    {"keyword": "CI 수정",             "target_l2": "work_core",          "confidence_floor": 0.5},
    {"keyword": "CI",                 "target_l2": "work_core",          "confidence_floor": 0.45},
    {"keyword": "배포 준비",           "target_l2": "work_core",          "confidence_floor": 0.5},
    {"keyword": "서버 배포",           "target_l2": "work_core",          "confidence_floor": 0.55},
    {"keyword": "모델 배포",           "target_l2": "work_core",          "confidence_floor": 0.55},
    {"keyword": "프로덕션 배포",       "target_l2": "work_core",          "confidence_floor": 0.55},
    {"keyword": "릴리즈 검증",         "target_l2": "work_core",          "confidence_floor": 0.5},
    {"keyword": "디버깅",              "target_l2": "work_core",          "confidence_floor": 0.6},
    {"keyword": "리팩토링",            "target_l2": "work_core",          "confidence_floor": 0.6},
    {"keyword": "새 기능 구현",        "target_l2": "work_core",          "confidence_floor": 0.5},
    {"keyword": "기능 구현",           "target_l2": "work_core",          "confidence_floor": 0.5},
    {"keyword": "버그 수정",           "target_l2": "work_core",          "confidence_floor": 0.55},
    {"keyword": "UI 버그",             "target_l2": "work_core",          "confidence_floor": 0.5},
    {"keyword": "로그 분석",           "target_l2": "work_core",          "confidence_floor": 0.45},
    {"keyword": "모니터링",            "target_l2": "work_core",          "confidence_floor": 0.45},
    {"keyword": "모니터링 대시보드",   "target_l2": "work_core",          "confidence_floor": 0.5},
    {"keyword": "자동화 테스트",       "target_l2": "work_core",          "confidence_floor": 0.5},
    {"keyword": "테스트 코드",         "target_l2": "work_core",          "confidence_floor": 0.5},
    {"keyword": "회귀 테스트",         "target_l2": "work_core",          "confidence_floor": 0.5},
    {"keyword": "테스트 케이스",       "target_l2": "work_core",          "confidence_floor": 0.45},

    {"keyword": "피처 엔지니어링",     "target_l2": "data_analysis_res",  "confidence_floor": 0.5},
    {"keyword": "모델 학습",           "target_l2": "data_analysis_res",  "confidence_floor": 0.5},
    {"keyword": "파이프라인 구축",     "target_l2": "work_core",          "confidence_floor": 0.5},

    {"keyword": "차팅",                "target_l2": null,                 "confidence_floor": 0.0, "note": "의료 전문 — V3 갭이므로 NEEDS_CONTEXT로 폴백"},
    {"keyword": "환자 투약",           "target_l2": null,                 "confidence_floor": 0.0, "note": "의료 갭"},
    {"keyword": "드레싱 교체",         "target_l2": null,                 "confidence_floor": 0.0, "note": "의료 갭"},
    {"keyword": "처방 조제",           "target_l2": null,                 "confidence_floor": 0.0, "note": "의료 갭"},
    {"keyword": "바이탈 체크",         "target_l2": null,                 "confidence_floor": 0.0, "note": "의료 갭"},
    {"keyword": "인수인계",            "target_l2": "work_planning",      "confidence_floor": 0.4},

    {"keyword": "신호 및 시스템",      "target_l2": "study_solo",         "confidence_floor": 0.5},
    {"keyword": "과학 공부",           "target_l2": "study_solo",         "confidence_floor": 0.5},
    {"keyword": "수학 문제",           "target_l2": "study_solo",         "confidence_floor": 0.5},
    {"keyword": "자습서",              "target_l2": "study_solo",         "confidence_floor": 0.45},
    {"keyword": "시험공부",            "target_l2": "exam_prep",          "confidence_floor": 0.55}
  ]
}
